mkpdf/__init__.py
mkpdf/cli.py
mkpdf/config.py
mkpdf/core.py
mkpdf/exceptions.py
mkpdf/logger.py
mkpdf/progress.py
pdfforge-1.0.1.dist-info/licenses/LICENSE
tests/__init__.py
tests/test_core.py
tests/test_utils.py
pdfforge-1.0.1.dist-info/METADATA
pdfforge-1.0.1.dist-info/WHEEL
pdfforge-1.0.1.dist-info/entry_points.txt
pdfforge-1.0.1.dist-info/top_level.txt
pdfforge-1.0.1.dist-info/RECORD
